[
  {
    "frame_id": 0,
    "keypoint_xyz": {
      "left_ear": [
        6,
        410,
        923
      ],
      "right_ear": [
        130,
        390,
        895
      ],
      "left_shoulder": [
        -104,
        520,
        1142
      ],
      "right_shoulder": [
        281,
        527,
        1151
      ],
      "left_elbow": [
        -195,
        405,
        1307
      ],
      "right_elbow": [
        358,
        387,
        1330
      ],
      "left_wrist": [
        -267,
        190,
        1494
      ],
      "right_wrist": [
        419,
        178,
        1497
      ]
    }
  },
  {
    "frame_id": 1,
    "keypoint_xyz": {
      "left_ear": [
        9,
        409,
        929
      ],
      "right_ear": [
        129,
        386,
        899
      ],
      "left_shoulder": [
        -101,
        525,
        1139
      ],
      "right_shoulder": [
        279,
        527,
        1153
      ],
      "left_elbow": [
        -195,
        408,
        1305
      ],
      "right_elbow": [
        358,
        388,
        1330
      ],
      "left_wrist": [
        -267,
        187,
        1496
      ],
      "right_wrist": [
        420,
        181,
        1494
      ]
    }
  },
  {
    "frame_id": 2,
    "keypoint_xyz": {
      "left_ear": [
        10,
        409,
        928
      ],
      "right_ear": [
        127,
        381,
        897
      ],
      "left_shoulder": [
        -104,
        518,
        1142
      ],
      "right_shoulder": [
        278,
        527,
        1153
      ],
      "left_elbow": [
        -190,
        403,
        1310
      ],
      "right_elbow": [
        357,
        387,
        1333
      ],
      "left_wrist": [
        -264,
        187,
        1494
      ],
      "right_wrist": [
        420,
        179,
        1499
      ]
    }
  },
  {
    "frame_id": 3,
    "keypoint_xyz": {
      "left_ear": [
        12,
        410,
        922
      ],
      "right_ear": [
        124,
        386,
        893
      ],
      "left_shoulder": [
        -100,
        525,
        1137
      ],
      "right_shoulder": [
        279,
        530,
        1151
      ],
      "left_elbow": [
        -195,
        405,
        1304
      ],
      "right_elbow": [
        355,
        388,
        1329
      ],
      "left_wrist": [
        -263,
        185,
        1493
      ],
      "right_wrist": [
        419,
        177,
        1502
      ]
    }
  },
  {
    "frame_id": 4,
    "keypoint_xyz": {
      "left_ear": [
        11,
        410,
        915
      ],
      "right_ear": [
        132,
        391,
        895
      ],
      "left_shoulder": [
        -94,
        526,
        1135
      ],
      "right_shoulder": [
        279,
        532,
        1150
      ],
      "left_elbow": [
        -194,
        413,
        1307
      ],
      "right_elbow": [
        353,
        392,
        1325
      ],
      "left_wrist": [
        -268,
        187,
        1493
      ],
      "right_wrist": [
        419,
        177,
        1500
      ]
    }
  },
  {
    "frame_id": 5,
    "keypoint_xyz": {
      "left_ear": [
        8,
        412,
        926
      ],
      "right_ear": [
        131,
        388,
        897
      ],
      "left_shoulder": [
        -95,
        524,
        1140
      ],
      "right_shoulder": [
        277,
        528,
        1153
      ],
      "left_elbow": [
        -193,
        409,
        1306
      ],
      "right_elbow": [
        353,
        389,
        1325
      ],
      "left_wrist": [
        -265,
        186,
        1491
      ],
      "right_wrist": [
        418,
        177,
        1499
      ]
    }
  },
  {
    "frame_id": 6,
    "keypoint_xyz": {
      "left_ear": [
        9,
        412,
        924
      ],
      "right_ear": [
        131,
        388,
        900
      ],
      "left_shoulder": [
        -91,
        529,
        1136
      ],
      "right_shoulder": [
        277,
        532,
        1150
      ],
      "left_elbow": [
        -193,
        418,
        1310
      ],
      "right_elbow": [
        353,
        389,
        1325
      ],
      "left_wrist": [
        -266,
        186,
        1491
      ],
      "right_wrist": [
        418,
        177,
        1497
      ]
    }
  },
  {
    "frame_id": 7,
    "keypoint_xyz": {
      "left_ear": [
        10,
        413,
        921
      ],
      "right_ear": [
        130,
        394,
        892
      ],
      "left_shoulder": [
        -98,
        529,
        1136
      ],
      "right_shoulder": [
        278,
        532,
        1151
      ],
      "left_elbow": [
        -191,
        411,
        1308
      ],
      "right_elbow": [
        354,
        390,
        1326
      ],
      "left_wrist": [
        -266,
        187,
        1492
      ],
      "right_wrist": [
        418,
        174,
        1499
      ]
    }
  },
  {
    "frame_id": 8,
    "keypoint_xyz": {
      "left_ear": [
        7,
        416,
        938
      ],
      "right_ear": [
        130,
        390,
        904
      ],
      "left_shoulder": [
        -95,
        529,
        1136
      ],
      "right_shoulder": [
        280,
        534,
        1149
      ],
      "left_elbow": [
        -190,
        419,
        1312
      ],
      "right_elbow": [
        354,
        386,
        1327
      ],
      "left_wrist": [
        -266,
        186,
        1491
      ],
      "right_wrist": [
        419,
        174,
        1500
      ]
    }
  },
  {
    "frame_id": 9,
    "keypoint_xyz": {
      "left_ear": [
        7,
        417,
        927
      ],
      "right_ear": [
        130,
        392,
        895
      ],
      "left_shoulder": [
        -96,
        531,
        1135
      ],
      "right_shoulder": [
        280,
        533,
        1151
      ],
      "left_elbow": [
        -191,
        412,
        1306
      ],
      "right_elbow": [
        351,
        388,
        1326
      ],
      "left_wrist": [
        -266,
        187,
        1492
      ],
      "right_wrist": [
        414,
        177,
        1496
      ]
    }
  },
  {
    "frame_id": 10,
    "keypoint_xyz": {
      "left_ear": [
        8,
        418,
        939
      ],
      "right_ear": [
        125,
        389,
        898
      ],
      "left_shoulder": [
        -99,
        531,
        1135
      ],
      "right_shoulder": [
        280,
        531,
        1149
      ],
      "left_elbow": [
        -191,
        412,
        1308
      ],
      "right_elbow": [
        352,
        386,
        1329
      ],
      "left_wrist": [
        -268,
        186,
        1489
      ],
      "right_wrist": [
        415,
        177,
        1498
      ]
    }
  },
  {
    "frame_id": 11,
    "keypoint_xyz": {
      "left_ear": [
        7,
        419,
        932
      ],
      "right_ear": [
        123,
        390,
        897
      ],
      "left_shoulder": [
        -98,
        527,
        1139
      ],
      "right_shoulder": [
        277,
        529,
        1150
      ],
      "left_elbow": [
        -192,
        409,
        1307
      ],
      "right_elbow": [
        350,
        386,
        1329
      ],
      "left_wrist": [
        -267,
        183,
        1493
      ],
      "right_wrist": [
        415,
        176,
        1503
      ]
    }
  },
  {
    "frame_id": 12,
    "keypoint_xyz": {
      "left_ear": [
        9,
        419,
        930
      ],
      "right_ear": [
        128,
        396,
        894
      ],
      "left_shoulder": [
        -99,
        529,
        1138
      ],
      "right_shoulder": [
        279,
        527,
        1152
      ],
      "left_elbow": [
        -192,
        409,
        1307
      ],
      "right_elbow": [
        351,
        385,
        1331
      ],
      "left_wrist": [
        -266,
        185,
        1492
      ],
      "right_wrist": [
        411,
        177,
        1501
      ]
    }
  },
  {
    "frame_id": 13,
    "keypoint_xyz": {
      "left_ear": [
        8,
        424,
        942
      ],
      "right_ear": [
        128,
        396,
        898
      ],
      "left_shoulder": [
        -97,
        525,
        1138
      ],
      "right_shoulder": [
        278,
        527,
        1152
      ],
      "left_elbow": [
        -195,
        408,
        1307
      ],
      "right_elbow": [
        353,
        382,
        1334
      ],
      "left_wrist": [
        -268,
        190,
        1492
      ],
      "right_wrist": [
        413,
        177,
        1502
      ]
    }
  },
  {
    "frame_id": 14,
    "keypoint_xyz": {
      "left_ear": [
        10,
        423,
        944
      ],
      "right_ear": [
        121,
        388,
        897
      ],
      "left_shoulder": [
        -94,
        532,
        1133
      ],
      "right_shoulder": [
        278,
        525,
        1153
      ],
      "left_elbow": [
        -196,
        414,
        1314
      ],
      "right_elbow": [
        353,
        381,
        1335
      ],
      "left_wrist": [
        -267,
        192,
        1497
      ],
      "right_wrist": [
        412,
        179,
        1499
      ]
    }
  },
  {
    "frame_id": 15,
    "keypoint_xyz": {
      "left_ear": [
        10,
        425,
        953
      ],
      "right_ear": [
        120,
        393,
        891
      ],
      "left_shoulder": [
        -106,
        520,
        1143
      ],
      "right_shoulder": [
        278,
        529,
        1151
      ],
      "left_elbow": [
        -202,
        405,
        1325
      ],
      "right_elbow": [
        354,
        384,
        1332
      ],
      "left_wrist": [
        -263,
        199,
        1498
      ],
      "right_wrist": [
        414,
        178,
        1505
      ]
    }
  },
  {
    "frame_id": 16,
    "keypoint_xyz": {
      "left_ear": [
        12,
        419,
        933
      ],
      "right_ear": [
        127,
        393,
        897
      ],
      "left_shoulder": [
        -107,
        524,
        1141
      ],
      "right_shoulder": [
        277,
        528,
        1149
      ],
      "left_elbow": [
        -203,
        412,
        1334
      ],
      "right_elbow": [
        353,
        386,
        1332
      ],
      "left_wrist": [
        -254,
        201,
        1504
      ],
      "right_wrist": [
        410,
        182,
        1503
      ]
    }
  },
  {
    "frame_id": 17,
    "keypoint_xyz": {
      "left_ear": [
        11,
        420,
        941
      ],
      "right_ear": [
        140,
        397,
        907
      ],
      "left_shoulder": [
        -108,
        520,
        1147
      ],
      "right_shoulder": [
        278,
        528,
        1148
      ],
      "left_elbow": [
        -211,
        417,
        1355
      ],
      "right_elbow": [
        353,
        385,
        1335
      ],
      "left_wrist": [
        -241,
        208,
        1506
      ],
      "right_wrist": [
        409,
        183,
        1506
      ]
    }
  },
  {
    "frame_id": 18,
    "keypoint_xyz": {
      "left_ear": [
        8,
        418,
        929
      ],
      "right_ear": [
        134,
        396,
        897
      ],
      "left_shoulder": [
        -109,
        527,
        1141
      ],
      "right_shoulder": [
        277,
        531,
        1144
      ],
      "left_elbow": [
        -206,
        427,
        1354
      ],
      "right_elbow": [
        354,
        388,
        1331
      ],
      "left_wrist": [
        -235,
        218,
        1509
      ],
      "right_wrist": [
        409,
        184,
        1507
      ]
    }
  },
  {
    "frame_id": 19,
    "keypoint_xyz": {
      "left_ear": [
        8,
        417,
        926
      ],
      "right_ear": [
        131,
        393,
        902
      ],
      "left_shoulder": [
        -117,
        523,
        1146
      ],
      "right_shoulder": [
        276,
        531,
        1145
      ],
      "left_elbow": [
        -209,
        436,
        1364
      ],
      "right_elbow": [
        349,
        396,
        1323
      ],
      "left_wrist": [
        -227,
        231,
        1507
      ],
      "right_wrist": [
        407,
        187,
        1505
      ]
    }
  },
  {
    "frame_id": 20,
    "keypoint_xyz": {
      "left_ear": [
        9,
        415,
        928
      ],
      "right_ear": [
        132,
        394,
        899
      ],
      "left_shoulder": [
        -115,
        527,
        1144
      ],
      "right_shoulder": [
        279,
        526,
        1145
      ],
      "left_elbow": [
        -209,
        445,
        1370
      ],
      "right_elbow": [
        355,
        392,
        1330
      ],
      "left_wrist": [
        -218,
        236,
        1506
      ],
      "right_wrist": [
        406,
        188,
        1508
      ]
    }
  },
  {
    "frame_id": 21,
    "keypoint_xyz": {
      "left_ear": [
        10,
        416,
        923
      ],
      "right_ear": [
        130,
        398,
        895
      ],
      "left_shoulder": [
        -119,
        528,
        1145
      ],
      "right_shoulder": [
        278,
        530,
        1143
      ],
      "left_elbow": [
        -201,
        453,
        1377
      ],
      "right_elbow": [
        355,
        394,
        1330
      ],
      "left_wrist": [
        -213,
        249,
        1504
      ],
      "right_wrist": [
        401,
        187,
        1513
      ]
    }
  },
  {
    "frame_id": 22,
    "keypoint_xyz": {
      "left_ear": [
        9,
        420,
        897
      ],
      "right_ear": [
        134,
        402,
        897
      ],
      "left_shoulder": [
        -118,
        530,
        1145
      ],
      "right_shoulder": [
        281,
        532,
        1141
      ],
      "left_elbow": [
        -196,
        465,
        1378
      ],
      "right_elbow": [
        356,
        391,
        1334
      ],
      "left_wrist": [
        -207,
        262,
        1499
      ],
      "right_wrist": [
        400,
        186,
        1519
      ]
    }
  },
  {
    "frame_id": 23,
    "keypoint_xyz": {
      "left_ear": [
        12,
        419,
        901
      ],
      "right_ear": [
        134,
        402,
        903
      ],
      "left_shoulder": [
        -118,
        530,
        1149
      ],
      "right_shoulder": [
        283,
        534,
        1137
      ],
      "left_elbow": [
        -192,
        480,
        1372
      ],
      "right_elbow": [
        354,
        396,
        1333
      ],
      "left_wrist": [
        -199,
        269,
        1499
      ],
      "right_wrist": [
        393,
        193,
        1512
      ]
    }
  },
  {
    "frame_id": 24,
    "keypoint_xyz": {
      "left_ear": [
        10,
        421,
        903
      ],
      "right_ear": [
        133,
        407,
        902
      ],
      "left_shoulder": [
        -123,
        534,
        1151
      ],
      "right_shoulder": [
        282,
        538,
        1136
      ],
      "left_elbow": [
        -193,
        472,
        1386
      ],
      "right_elbow": [
        354,
        398,
        1334
      ],
      "left_wrist": [
        -191,
        269,
        1500
      ],
      "right_wrist": [
        388,
        200,
        1511
      ]
    }
  },
  {
    "frame_id": 25,
    "keypoint_xyz": {
      "left_ear": [
        10,
        427,
        896
      ],
      "right_ear": [
        130,
        406,
        903
      ],
      "left_shoulder": [
        -119,
        537,
        1148
      ],
      "right_shoulder": [
        281,
        539,
        1136
      ],
      "left_elbow": [
        -189,
        477,
        1387
      ],
      "right_elbow": [
        352,
        404,
        1332
      ],
      "left_wrist": [
        -177,
        277,
        1500
      ],
      "right_wrist": [
        381,
        205,
        1516
      ]
    }
  },
  {
    "frame_id": 26,
    "keypoint_xyz": {
      "left_ear": [
        5,
        432,
        896
      ],
      "right_ear": [
        130,
        411,
        903
      ],
      "left_shoulder": [
        -127,
        538,
        1153
      ],
      "right_shoulder": [
        280,
        544,
        1133
      ],
      "left_elbow": [
        -190,
        477,
        1395
      ],
      "right_elbow": [
        350,
        403,
        1339
      ],
      "left_wrist": [
        -168,
        277,
        1507
      ],
      "right_wrist": [
        375,
        211,
        1519
      ]
    }
  },
  {
    "frame_id": 27,
    "keypoint_xyz": {
      "left_ear": [
        8,
        432,
        895
      ],
      "right_ear": [
        125,
        416,
        891
      ],
      "left_shoulder": [
        -128,
        541,
        1151
      ],
      "right_shoulder": [
        279,
        549,
        1133
      ],
      "left_elbow": [
        -186,
        478,
        1403
      ],
      "right_elbow": [
        346,
        418,
        1339
      ],
      "left_wrist": [
        -159,
        282,
        1508
      ],
      "right_wrist": [
        362,
        218,
        1520
      ]
    }
  },
  {
    "frame_id": 28,
    "keypoint_xyz": {
      "left_ear": [
        5,
        436,
        897
      ],
      "right_ear": [
        119,
        419,
        882
      ],
      "left_shoulder": [
        -130,
        540,
        1155
      ],
      "right_shoulder": [
        278,
        550,
        1132
      ],
      "left_elbow": [
        -184,
        476,
        1418
      ],
      "right_elbow": [
        342,
        419,
        1343
      ],
      "left_wrist": [
        -144,
        290,
        1505
      ],
      "right_wrist": [
        354,
        227,
        1514
      ]
    }
  },
  {
    "frame_id": 29,
    "keypoint_xyz": {
      "left_ear": [
        3,
        437,
        906
      ],
      "right_ear": [
        116,
        421,
        885
      ],
      "left_shoulder": [
        -130,
        543,
        1156
      ],
      "right_shoulder": [
        276,
        555,
        1134
      ],
      "left_elbow": [
        -180,
        475,
        1421
      ],
      "right_elbow": [
        345,
        423,
        1347
      ],
      "left_wrist": [
        -133,
        295,
        1509
      ],
      "right_wrist": [
        347,
        232,
        1525
      ]
    }
  },
  {
    "frame_id": 30,
    "keypoint_xyz": {
      "left_ear": [
        6,
        440,
        895
      ],
      "right_ear": [
        117,
        422,
        893
      ],
      "left_shoulder": [
        -126,
        549,
        1153
      ],
      "right_shoulder": [
        277,
        560,
        1134
      ],
      "left_elbow": [
        -181,
        482,
        1419
      ],
      "right_elbow": [
        343,
        428,
        1353
      ],
      "left_wrist": [
        -120,
        307,
        1512
      ],
      "right_wrist": [
        337,
        238,
        1532
      ]
    }
  },
  {
    "frame_id": 31,
    "keypoint_xyz": {
      "left_ear": [
        7,
        445,
        902
      ],
      "right_ear": [
        122,
        430,
        896
      ],
      "left_shoulder": [
        -127,
        553,
        1151
      ],
      "right_shoulder": [
        275,
        563,
        1137
      ],
      "left_elbow": [
        -178,
        480,
        1421
      ],
      "right_elbow": [
        342,
        431,
        1358
      ],
      "left_wrist": [
        -109,
        307,
        1520
      ],
      "right_wrist": [
        327,
        247,
        1531
      ]
    }
  },
  {
    "frame_id": 32,
    "keypoint_xyz": {
      "left_ear": [
        6,
        449,
        908
      ],
      "right_ear": [
        123,
        438,
        889
      ],
      "left_shoulder": [
        -127,
        556,
        1151
      ],
      "right_shoulder": [
        273,
        568,
        1135
      ],
      "left_elbow": [
        -176,
        486,
        1418
      ],
      "right_elbow": [
        338,
        442,
        1357
      ],
      "left_wrist": [
        -105,
        308,
        1521
      ],
      "right_wrist": [
        318,
        252,
        1536
      ]
    }
  },
  {
    "frame_id": 33,
    "keypoint_xyz": {
      "left_ear": [
        5,
        454,
        900
      ],
      "right_ear": [
        126,
        445,
        894
      ],
      "left_shoulder": [
        -126,
        559,
        1149
      ],
      "right_shoulder": [
        273,
        573,
        1139
      ],
      "left_elbow": [
        -175,
        480,
        1422
      ],
      "right_elbow": [
        336,
        450,
        1359
      ],
      "left_wrist": [
        -93,
        309,
        1527
      ],
      "right_wrist": [
        311,
        257,
        1536
      ]
    }
  },
  {
    "frame_id": 34,
    "keypoint_xyz": {
      "left_ear": [
        2,
        465,
        897
      ],
      "right_ear": [
        126,
        452,
        887
      ],
      "left_shoulder": [
        -129,
        562,
        1148
      ],
      "right_shoulder": [
        275,
        577,
        1138
      ],
      "left_elbow": [
        -171,
        476,
        1422
      ],
      "right_elbow": [
        335,
        461,
        1357
      ],
      "left_wrist": [
        -84,
        307,
        1533
      ],
      "right_wrist": [
        302,
        262,
        1537
      ]
    }
  },
  {
    "frame_id": 35,
    "keypoint_xyz": {
      "left_ear": [
        6,
        461,
        900
      ],
      "right_ear": [
        130,
        457,
        897
      ],
      "left_shoulder": [
        -123,
        565,
        1146
      ],
      "right_shoulder": [
        275,
        580,
        1141
      ],
      "left_elbow": [
        -171,
        482,
        1423
      ],
      "right_elbow": [
        336,
        466,
        1355
      ],
      "left_wrist": [
        -77,
        315,
        1531
      ],
      "right_wrist": [
        288,
        272,
        1537
      ]
    }
  },
  {
    "frame_id": 36,
    "keypoint_xyz": {
      "left_ear": [
        6,
        465,
        906
      ],
      "right_ear": [
        130,
        460,
        894
      ],
      "left_shoulder": [
        -121,
        568,
        1143
      ],
      "right_shoulder": [
        271,
        581,
        1142
      ],
      "left_elbow": [
        -170,
        485,
        1420
      ],
      "right_elbow": [
        334,
        469,
        1360
      ],
      "left_wrist": [
        -72,
        323,
        1532
      ],
      "right_wrist": [
        277,
        286,
        1531
      ]
    }
  },
  {
    "frame_id": 37,
    "keypoint_xyz": {
      "left_ear": [
        4,
        470,
        896
      ],
      "right_ear": [
        132,
        469,
        894
      ],
      "left_shoulder": [
        -125,
        567,
        1149
      ],
      "right_shoulder": [
        274,
        587,
        1141
      ],
      "left_elbow": [
        -170,
        486,
        1418
      ],
      "right_elbow": [
        335,
        489,
        1348
      ],
      "left_wrist": [
        -72,
        323,
        1530
      ],
      "right_wrist": [
        275,
        300,
        1519
      ]
    }
  },
  {
    "frame_id": 38,
    "keypoint_xyz": {
      "left_ear": [
        6,
        474,
        893
      ],
      "right_ear": [
        133,
        475,
        889
      ],
      "left_shoulder": [
        -122,
        570,
        1147
      ],
      "right_shoulder": [
        273,
        588,
        1144
      ],
      "left_elbow": [
        -169,
        482,
        1420
      ],
      "right_elbow": [
        333,
        488,
        1361
      ],
      "left_wrist": [
        -65,
        325,
        1533
      ],
      "right_wrist": [
        260,
        307,
        1528
      ]
    }
  },
  {
    "frame_id": 39,
    "keypoint_xyz": {
      "left_ear": [
        4,
        480,
        890
      ],
      "right_ear": [
        132,
        480,
        889
      ],
      "left_shoulder": [
        -128,
        572,
        1151
      ],
      "right_shoulder": [
        273,
        590,
        1143
      ],
      "left_elbow": [
        -169,
        486,
        1418
      ],
      "right_elbow": [
        332,
        491,
        1362
      ],
      "left_wrist": [
        -64,
        322,
        1532
      ],
      "right_wrist": [
        253,
        315,
        1526
      ]
    }
  },
  {
    "frame_id": 40,
    "keypoint_xyz": {
      "left_ear": [
        7,
        481,
        900
      ],
      "right_ear": [
        134,
        481,
        896
      ],
      "left_shoulder": [
        -119,
        575,
        1143
      ],
      "right_shoulder": [
        273,
        591,
        1147
      ],
      "left_elbow": [
        -166,
        489,
        1414
      ],
      "right_elbow": [
        324,
        491,
        1366
      ],
      "left_wrist": [
        -62,
        323,
        1533
      ],
      "right_wrist": [
        240,
        320,
        1530
      ]
    }
  },
  {
    "frame_id": 41,
    "keypoint_xyz": {
      "left_ear": [
        7,
        482,
        899
      ],
      "right_ear": [
        130,
        479,
        894
      ],
      "left_shoulder": [
        -121,
        578,
        1145
      ],
      "right_shoulder": [
        269,
        600,
        1144
      ],
      "left_elbow": [
        -164,
        489,
        1418
      ],
      "right_elbow": [
        324,
        494,
        1366
      ],
      "left_wrist": [
        -62,
        323,
        1530
      ],
      "right_wrist": [
        232,
        326,
        1532
      ]
    }
  },
  {
    "frame_id": 42,
    "keypoint_xyz": {
      "left_ear": [
        7,
        484,
        900
      ],
      "right_ear": [
        132,
        480,
        898
      ],
      "left_shoulder": [
        -121,
        576,
        1147
      ],
      "right_shoulder": [
        272,
        599,
        1146
      ],
      "left_elbow": [
        -162,
        487,
        1424
      ],
      "right_elbow": [
        324,
        499,
        1368
      ],
      "left_wrist": [
        -59,
        321,
        1530
      ],
      "right_wrist": [
        222,
        332,
        1530
      ]
    }
  },
  {
    "frame_id": 43,
    "keypoint_xyz": {
      "left_ear": [
        8,
        489,
        909
      ],
      "right_ear": [
        132,
        482,
        900
      ],
      "left_shoulder": [
        -120,
        578,
        1147
      ],
      "right_shoulder": [
        269,
        601,
        1146
      ],
      "left_elbow": [
        -161,
        485,
        1420
      ],
      "right_elbow": [
        322,
        500,
        1370
      ],
      "left_wrist": [
        -62,
        321,
        1531
      ],
      "right_wrist": [
        209,
        341,
        1531
      ]
    }
  },
  {
    "frame_id": 44,
    "keypoint_xyz": {
      "left_ear": [
        7,
        493,
        908
      ],
      "right_ear": [
        135,
        485,
        902
      ],
      "left_shoulder": [
        -118,
        580,
        1145
      ],
      "right_shoulder": [
        274,
        599,
        1149
      ],
      "left_elbow": [
        -161,
        485,
        1420
      ],
      "right_elbow": [
        322,
        502,
        1371
      ],
      "left_wrist": [
        -62,
        319,
        1529
      ],
      "right_wrist": [
        201,
        347,
        1522
      ]
    }
  },
  {
    "frame_id": 45,
    "keypoint_xyz": {
      "left_ear": [
        7,
        495,
        910
      ],
      "right_ear": [
        136,
        486,
        907
      ],
      "left_shoulder": [
        -117,
        583,
        1143
      ],
      "right_shoulder": [
        269,
        601,
        1150
      ],
      "left_elbow": [
        -162,
        483,
        1418
      ],
      "right_elbow": [
        328,
        507,
        1372
      ],
      "left_wrist": [
        -55,
        317,
        1535
      ],
      "right_wrist": [
        194,
        350,
        1516
      ]
    }
  },
  {
    "frame_id": 46,
    "keypoint_xyz": {
      "left_ear": [
        10,
        498,
        914
      ],
      "right_ear": [
        135,
        485,
        902
      ],
      "left_shoulder": [
        -114,
        583,
        1143
      ],
      "right_shoulder": [
        271,
        600,
        1153
      ],
      "left_elbow": [
        -161,
        482,
        1419
      ],
      "right_elbow": [
        326,
        507,
        1374
      ],
      "left_wrist": [
        -59,
        319,
        1533
      ],
      "right_wrist": [
        188,
        350,
        1509
      ]
    }
  },
  {
    "frame_id": 47,
    "keypoint_xyz": {
      "left_ear": [
        10,
        502,
        924
      ],
      "right_ear": [
        139,
        486,
        913
      ],
      "left_shoulder": [
        -117,
        583,
        1143
      ],
      "right_shoulder": [
        273,
        605,
        1149
      ],
      "left_elbow": [
        -164,
        483,
        1417
      ],
      "right_elbow": [
        330,
        513,
        1375
      ],
      "left_wrist": [
        -57,
        318,
        1532
      ],
      "right_wrist": [
        187,
        354,
        1504
      ]
    }
  },
  {
    "frame_id": 48,
    "keypoint_xyz": {
      "left_ear": [
        11,
        507,
        933
      ],
      "right_ear": [
        139,
        488,
        912
      ],
      "left_shoulder": [
        -120,
        583,
        1142
      ],
      "right_shoulder": [
        273,
        601,
        1151
      ],
      "left_elbow": [
        -164,
        482,
        1418
      ],
      "right_elbow": [
        333,
        517,
        1373
      ],
      "left_wrist": [
        -60,
        320,
        1531
      ],
      "right_wrist": [
        192,
        357,
        1501
      ]
    }
  },
  {
    "frame_id": 49,
    "keypoint_xyz": {
      "left_ear": [
        10,
        509,
        930
      ],
      "right_ear": [
        137,
        484,
        912
      ],
      "left_shoulder": [
        -117,
        582,
        1142
      ],
      "right_shoulder": [
        273,
        603,
        1149
      ],
      "left_elbow": [
        -165,
        489,
        1417
      ],
      "right_elbow": [
        337,
        521,
        1373
      ],
      "left_wrist": [
        -62,
        320,
        1533
      ],
      "right_wrist": [
        195,
        356,
        1498
      ]
    }
  },
  {
    "frame_id": 50,
    "keypoint_xyz": {
      "left_ear": [
        12,
        512,
        944
      ],
      "right_ear": [
        142,
        489,
        913
      ],
      "left_shoulder": [
        -118,
        583,
        1142
      ],
      "right_shoulder": [
        280,
        600,
        1153
      ],
      "left_elbow": [
        -165,
        489,
        1416
      ],
      "right_elbow": [
        339,
        522,
        1371
      ],
      "left_wrist": [
        -67,
        321,
        1529
      ],
      "right_wrist": [
        203,
        354,
        1499
      ]
    }
  },
  {
    "frame_id": 51,
    "keypoint_xyz": {
      "left_ear": [
        12,
        510,
        939
      ],
      "right_ear": [
        142,
        487,
        907
      ],
      "left_shoulder": [
        -121,
        581,
        1145
      ],
      "right_shoulder": [
        279,
        602,
        1150
      ],
      "left_elbow": [
        -167,
        486,
        1416
      ],
      "right_elbow": [
        341,
        524,
        1362
      ],
      "left_wrist": [
        -65,
        325,
        1534
      ],
      "right_wrist": [
        212,
        351,
        1498
      ]
    }
  },
  {
    "frame_id": 52,
    "keypoint_xyz": {
      "left_ear": [
        11,
        513,
        950
      ],
      "right_ear": [
        142,
        484,
        911
      ],
      "left_shoulder": [
        -122,
        578,
        1145
      ],
      "right_shoulder": [
        283,
        601,
        1153
      ],
      "left_elbow": [
        -167,
        491,
        1418
      ],
      "right_elbow": [
        342,
        520,
        1374
      ],
      "left_wrist": [
        -70,
        322,
        1532
      ],
      "right_wrist": [
        218,
        343,
        1499
      ]
    }
  },
  {
    "frame_id": 53,
    "keypoint_xyz": {
      "left_ear": [
        15,
        500,
        931
      ],
      "right_ear": [
        144,
        484,
        911
      ],
      "left_shoulder": [
        -118,
        580,
        1146
      ],
      "right_shoulder": [
        282,
        600,
        1153
      ],
      "left_elbow": [
        -164,
        488,
        1418
      ],
      "right_elbow": [
        340,
        517,
        1374
      ],
      "left_wrist": [
        -77,
        326,
        1530
      ],
      "right_wrist": [
        228,
        340,
        1501
      ]
    }
  },
  {
    "frame_id": 54,
    "keypoint_xyz": {
      "left_ear": [
        15,
        495,
        914
      ],
      "right_ear": [
        140,
        481,
        899
      ],
      "left_shoulder": [
        -118,
        578,
        1145
      ],
      "right_shoulder": [
        284,
        596,
        1155
      ],
      "left_elbow": [
        -165,
        488,
        1418
      ],
      "right_elbow": [
        345,
        517,
        1374
      ],
      "left_wrist": [
        -80,
        327,
        1525
      ],
      "right_wrist": [
        238,
        331,
        1505
      ]
    }
  },
  {
    "frame_id": 55,
    "keypoint_xyz": {
      "left_ear": [
        19,
        492,
        923
      ],
      "right_ear": [
        140,
        474,
        904
      ],
      "left_shoulder": [
        -111,
        578,
        1142
      ],
      "right_shoulder": [
        283,
        599,
        1151
      ],
      "left_elbow": [
        -164,
        484,
        1419
      ],
      "right_elbow": [
        350,
        515,
        1376
      ],
      "left_wrist": [
        -82,
        320,
        1526
      ],
      "right_wrist": [
        250,
        324,
        1511
      ]
    }
  },
  {
    "frame_id": 56,
    "keypoint_xyz": {
      "left_ear": [
        16,
        490,
        914
      ],
      "right_ear": [
        139,
        474,
        899
      ],
      "left_shoulder": [
        -115,
        581,
        1141
      ],
      "right_shoulder": [
        285,
        598,
        1151
      ],
      "left_elbow": [
        -167,
        498,
        1418
      ],
      "right_elbow": [
        349,
        512,
        1380
      ],
      "left_wrist": [
        -83,
        324,
        1527
      ],
      "right_wrist": [
        262,
        322,
        1513
      ]
    }
  },
  {
    "frame_id": 57,
    "keypoint_xyz": {
      "left_ear": [
        16,
        488,
        910
      ],
      "right_ear": [
        137,
        467,
        903
      ],
      "left_shoulder": [
        -118,
        575,
        1145
      ],
      "right_shoulder": [
        287,
        595,
        1153
      ],
      "left_elbow": [
        -164,
        489,
        1418
      ],
      "right_elbow": [
        353,
        515,
        1371
      ],
      "left_wrist": [
        -85,
        320,
        1527
      ],
      "right_wrist": [
        277,
        323,
        1514
      ]
    }
  },
  {
    "frame_id": 58,
    "keypoint_xyz": {
      "left_ear": [
        18,
        490,
        943
      ],
      "right_ear": [
        136,
        465,
        896
      ],
      "left_shoulder": [
        -118,
        575,
        1147
      ],
      "right_shoulder": [
        292,
        593,
        1156
      ],
      "left_elbow": [
        -164,
        486,
        1421
      ],
      "right_elbow": [
        354,
        509,
        1383
      ],
      "left_wrist": [
        -87,
        318,
        1529
      ],
      "right_wrist": [
        288,
        324,
        1518
      ]
    }
  },
  {
    "frame_id": 59,
    "keypoint_xyz": {
      "left_ear": [
        16,
        489,
        941
      ],
      "right_ear": [
        136,
        462,
        896
      ],
      "left_shoulder": [
        -112,
        576,
        1142
      ],
      "right_shoulder": [
        291,
        592,
        1152
      ],
      "left_elbow": [
        -165,
        500,
        1419
      ],
      "right_elbow": [
        355,
        508,
        1381
      ],
      "left_wrist": [
        -97,
        317,
        1525
      ],
      "right_wrist": [
        293,
        325,
        1521
      ]
    }
  },
  {
    "frame_id": 60,
    "keypoint_xyz": {
      "left_ear": [
        17,
        484,
        928
      ],
      "right_ear": [
        136,
        459,
        901
      ],
      "left_shoulder": [
        -117,
        569,
        1150
      ],
      "right_shoulder": [
        291,
        591,
        1155
      ],
      "left_elbow": [
        -163,
        488,
        1422
      ],
      "right_elbow": [
        356,
        505,
        1388
      ],
      "left_wrist": [
        -100,
        315,
        1526
      ],
      "right_wrist": [
        301,
        322,
        1530
      ]
    }
  },
  {
    "frame_id": 61,
    "keypoint_xyz": {
      "left_ear": [
        18,
        480,
        918
      ],
      "right_ear": [
        137,
        458,
        903
      ],
      "left_shoulder": [
        -115,
        572,
        1144
      ],
      "right_shoulder": [
        293,
        589,
        1153
      ],
      "left_elbow": [
        -164,
        488,
        1420
      ],
      "right_elbow": [
        357,
        502,
        1391
      ],
      "left_wrist": [
        -113,
        310,
        1526
      ],
      "right_wrist": [
        299,
        326,
        1536
      ]
    }
  },
  {
    "frame_id": 62,
    "keypoint_xyz": {
      "left_ear": [
        18,
        479,
        933
      ],
      "right_ear": [
        132,
        452,
        895
      ],
      "left_shoulder": [
        -109,
        571,
        1142
      ],
      "right_shoulder": [
        286,
        589,
        1154
      ],
      "left_elbow": [
        -165,
        481,
        1424
      ],
      "right_elbow": [
        355,
        503,
        1391
      ],
      "left_wrist": [
        -118,
        309,
        1529
      ],
      "right_wrist": [
        304,
        326,
        1544
      ]
    }
  },
  {
    "frame_id": 63,
    "keypoint_xyz": {
      "left_ear": [
        18,
        478,
        938
      ],
      "right_ear": [
        132,
        447,
        901
      ],
      "left_shoulder": [
        -102,
        571,
        1135
      ],
      "right_shoulder": [
        283,
        587,
        1155
      ],
      "left_elbow": [
        -166,
        481,
        1421
      ],
      "right_elbow": [
        351,
        509,
        1386
      ],
      "left_wrist": [
        -125,
        307,
        1534
      ],
      "right_wrist": [
        298,
        331,
        1549
      ]
    }
  },
  {
    "frame_id": 64,
    "keypoint_xyz": {
      "left_ear": [
        18,
        482,
        962
      ],
      "right_ear": [
        137,
        446,
        912
      ],
      "left_shoulder": [
        -106,
        572,
        1139
      ],
      "right_shoulder": [
        287,
        585,
        1157
      ],
      "left_elbow": [
        -166,
        474,
        1422
      ],
      "right_elbow": [
        349,
        505,
        1392
      ],
      "left_wrist": [
        -132,
        306,
        1537
      ],
      "right_wrist": [
        291,
        335,
        1553
      ]
    }
  },
  {
    "frame_id": 65,
    "keypoint_xyz": {
      "left_ear": [
        17,
        489,
        984
      ],
      "right_ear": [
        133,
        441,
        906
      ],
      "left_shoulder": [
        -108,
        568,
        1144
      ],
      "right_shoulder": [
        289,
        584,
        1157
      ],
      "left_elbow": [
        -164,
        474,
        1422
      ],
      "right_elbow": [
        349,
        505,
        1395
      ],
      "left_wrist": [
        -138,
        303,
        1541
      ],
      "right_wrist": [
        284,
        336,
        1560
      ]
    }
  },
  {
    "frame_id": 66,
    "keypoint_xyz": {
      "left_ear": [
        19,
        476,
        961
      ],
      "right_ear": [
        132,
        438,
        897
      ],
      "left_shoulder": [
        -105,
        573,
        1138
      ],
      "right_shoulder": [
        285,
        584,
        1157
      ],
      "left_elbow": [
        -161,
        474,
        1421
      ],
      "right_elbow": [
        348,
        507,
        1393
      ],
      "left_wrist": [
        -138,
        302,
        1543
      ],
      "right_wrist": [
        277,
        340,
        1561
      ]
    }
  },
  {
    "frame_id": 67,
    "keypoint_xyz": {
      "left_ear": [
        16,
        497,
        1018
      ],
      "right_ear": [
        134,
        436,
        911
      ],
      "left_shoulder": [
        -105,
        568,
        1144
      ],
      "right_shoulder": [
        286,
        578,
        1162
      ],
      "left_elbow": [
        -162,
        471,
        1426
      ],
      "right_elbow": [
        349,
        506,
        1396
      ],
      "left_wrist": [
        -143,
        298,
        1547
      ],
      "right_wrist": [
        274,
        341,
        1563
      ]
    }
  },
  {
    "frame_id": 68,
    "keypoint_xyz": {
      "left_ear": [
        0,
        0,
        0
      ],
      "right_ear": [
        137,
        435,
        920
      ],
      "left_shoulder": [
        -106,
        574,
        1141
      ],
      "right_shoulder": [
        286,
        581,
        1158
      ],
      "left_elbow": [
        -159,
        468,
        1427
      ],
      "right_elbow": [
        345,
        507,
        1398
      ],
      "left_wrist": [
        -143,
        296,
        1547
      ],
      "right_wrist": [
        271,
        342,
        1564
      ]
    }
  },
  {
    "frame_id": 69,
    "keypoint_xyz": {
      "left_ear": [
        0,
        0,
        0
      ],
      "right_ear": [
        131,
        433,
        906
      ],
      "left_shoulder": [
        -109,
        574,
        1141
      ],
      "right_shoulder": [
        285,
        580,
        1159
      ],
      "left_elbow": [
        -156,
        465,
        1431
      ],
      "right_elbow": [
        343,
        504,
        1402
      ],
      "left_wrist": [
        -147,
        293,
        1548
      ],
      "right_wrist": [
        264,
        343,
        1564
      ]
    }
  },
  {
    "frame_id": 70,
    "keypoint_xyz": {
      "left_ear": [
        12,
        474,
        957
      ],
      "right_ear": [
        129,
        434,
        904
      ],
      "left_shoulder": [
        -101,
        573,
        1141
      ],
      "right_shoulder": [
        282,
        578,
        1162
      ],
      "left_elbow": [
        -153,
        466,
        1426
      ],
      "right_elbow": [
        345,
        508,
        1399
      ],
      "left_wrist": [
        -153,
        292,
        1545
      ],
      "right_wrist": [
        261,
        343,
        1566
      ]
    }
  },
  {
    "frame_id": 71,
    "keypoint_xyz": {
      "left_ear": [
        13,
        469,
        946
      ],
      "right_ear": [
        134,
        434,
        906
      ],
      "left_shoulder": [
        -110,
        574,
        1144
      ],
      "right_shoulder": [
        288,
        575,
        1160
      ],
      "left_elbow": [
        -156,
        465,
        1430
      ],
      "right_elbow": [
        343,
        504,
        1406
      ],
      "left_wrist": [
        -152,
        292,
        1544
      ],
      "right_wrist": [
        260,
        343,
        1568
      ]
    }
  },
  {
    "frame_id": 72,
    "keypoint_xyz": {
      "left_ear": [
        0,
        0,
        0
      ],
      "right_ear": [
        131,
        434,
        904
      ],
      "left_shoulder": [
        -106,
        573,
        1142
      ],
      "right_shoulder": [
        285,
        574,
        1161
      ],
      "left_elbow": [
        -157,
        460,
        1438
      ],
      "right_elbow": [
        340,
        503,
        1406
      ],
      "left_wrist": [
        -157,
        290,
        1548
      ],
      "right_wrist": [
        260,
        345,
        1567
      ]
    }
  },
  {
    "frame_id": 73,
    "keypoint_xyz": {
      "left_ear": [
        0,
        0,
        0
      ],
      "right_ear": [
        130,
        433,
        909
      ],
      "left_shoulder": [
        -106,
        575,
        1138
      ],
      "right_shoulder": [
        283,
        574,
        1159
      ],
      "left_elbow": [
        -157,
        463,
        1426
      ],
      "right_elbow": [
        341,
        502,
        1405
      ],
      "left_wrist": [
        -157,
        289,
        1546
      ],
      "right_wrist": [
        259,
        345,
        1566
      ]
    }
  },
  {
    "frame_id": 74,
    "keypoint_xyz": {
      "left_ear": [
        0,
        0,
        0
      ],
      "right_ear": [
        130,
        432,
        906
      ],
      "left_shoulder": [
        -110,
        576,
        1141
      ],
      "right_shoulder": [
        282,
        576,
        1158
      ],
      "left_elbow": [
        -160,
        465,
        1422
      ],
      "right_elbow": [
        342,
        502,
        1409
      ],
      "left_wrist": [
        -157,
        290,
        1548
      ],
      "right_wrist": [
        260,
        342,
        1568
      ]
    }
  },
  {
    "frame_id": 75,
    "keypoint_xyz": {
      "left_ear": [
        14,
        477,
        963
      ],
      "right_ear": [
        128,
        431,
        895
      ],
      "left_shoulder": [
        -105,
        576,
        1137
      ],
      "right_shoulder": [
        283,
        576,
        1160
      ],
      "left_elbow": [
        -160,
        472,
        1421
      ],
      "right_elbow": [
        340,
        505,
        1403
      ],
      "left_wrist": [
        -157,
        289,
        1546
      ],
      "right_wrist": [
        259,
        345,
        1566
      ]
    }
  },
  {
    "frame_id": 76,
    "keypoint_xyz": {
      "left_ear": [
        14,
        487,
        989
      ],
      "right_ear": [
        129,
        433,
        905
      ],
      "left_shoulder": [
        -104,
        576,
        1138
      ],
      "right_shoulder": [
        281,
        578,
        1159
      ],
      "left_elbow": [
        -158,
        464,
        1429
      ],
      "right_elbow": [
        342,
        508,
        1399
      ],
      "left_wrist": [
        -158,
        289,
        1546
      ],
      "right_wrist": [
        259,
        346,
        1563
      ]
    }
  },
  {
    "frame_id": 77,
    "keypoint_xyz": {
      "left_ear": [
        13,
        480,
        971
      ],
      "right_ear": [
        129,
        432,
        901
      ],
      "left_shoulder": [
        -108,
        577,
        1139
      ],
      "right_shoulder": [
        283,
        575,
        1161
      ],
      "left_elbow": [
        -157,
        463,
        1434
      ],
      "right_elbow": [
        342,
        508,
        1400
      ],
      "left_wrist": [
        -155,
        289,
        1544
      ],
      "right_wrist": [
        259,
        345,
        1566
      ]
    }
  },
  {
    "frame_id": 78,
    "keypoint_xyz": {
      "left_ear": [
        13,
        481,
        975
      ],
      "right_ear": [
        133,
        436,
        914
      ],
      "left_shoulder": [
        -110,
        575,
        1141
      ],
      "right_shoulder": [
        282,
        578,
        1161
      ],
      "left_elbow": [
        -158,
        463,
        1433
      ],
      "right_elbow": [
        342,
        509,
        1398
      ],
      "left_wrist": [
        -157,
        288,
        1547
      ],
      "right_wrist": [
        262,
        347,
        1563
      ]
    }
  },
  {
    "frame_id": 79,
    "keypoint_xyz": {
      "left_ear": [
        14,
        474,
        959
      ],
      "right_ear": [
        129,
        437,
        894
      ],
      "left_shoulder": [
        -111,
        576,
        1141
      ],
      "right_shoulder": [
        283,
        578,
        1160
      ],
      "left_elbow": [
        -160,
        463,
        1434
      ],
      "right_elbow": [
        342,
        507,
        1400
      ],
      "left_wrist": [
        -157,
        289,
        1546
      ],
      "right_wrist": [
        262,
        345,
        1562
      ]
    }
  },
  {
    "frame_id": 80,
    "keypoint_xyz": {
      "left_ear": [
        14,
        470,
        948
      ],
      "right_ear": [
        131,
        437,
        902
      ],
      "left_shoulder": [
        -111,
        575,
        1139
      ],
      "right_shoulder": [
        285,
        577,
        1159
      ],
      "left_elbow": [
        -158,
        463,
        1435
      ],
      "right_elbow": [
        342,
        506,
        1402
      ],
      "left_wrist": [
        -153,
        289,
        1545
      ],
      "right_wrist": [
        263,
        346,
        1565
      ]
    }
  },
  {
    "frame_id": 81,
    "keypoint_xyz": {
      "left_ear": [
        15,
        475,
        964
      ],
      "right_ear": [
        131,
        436,
        908
      ],
      "left_shoulder": [
        -109,
        574,
        1143
      ],
      "right_shoulder": [
        284,
        577,
        1160
      ],
      "left_elbow": [
        -156,
        465,
        1431
      ],
      "right_elbow": [
        341,
        508,
        1401
      ],
      "left_wrist": [
        -153,
        292,
        1542
      ],
      "right_wrist": [
        261,
        347,
        1563
      ]
    }
  },
  {
    "frame_id": 82,
    "keypoint_xyz": {
      "left_ear": [
        13,
        474,
        954
      ],
      "right_ear": [
        128,
        437,
        897
      ],
      "left_shoulder": [
        -106,
        575,
        1141
      ],
      "right_shoulder": [
        284,
        581,
        1155
      ],
      "left_elbow": [
        -156,
        469,
        1424
      ],
      "right_elbow": [
        341,
        507,
        1400
      ],
      "left_wrist": [
        -153,
        290,
        1543
      ],
      "right_wrist": [
        261,
        346,
        1564
      ]
    }
  },
  {
    "frame_id": 83,
    "keypoint_xyz": {
      "left_ear": [
        15,
        473,
        958
      ],
      "right_ear": [
        129,
        435,
        904
      ],
      "left_shoulder": [
        -105,
        579,
        1139
      ],
      "right_shoulder": [
        283,
        578,
        1161
      ],
      "left_elbow": [
        -156,
        469,
        1425
      ],
      "right_elbow": [
        344,
        510,
        1401
      ],
      "left_wrist": [
        -153,
        292,
        1543
      ],
      "right_wrist": [
        262,
        346,
        1564
      ]
    }
  },
  {
    "frame_id": 84,
    "keypoint_xyz": {
      "left_ear": [
        13,
        479,
        968
      ],
      "right_ear": [
        131,
        438,
        908
      ],
      "left_shoulder": [
        -110,
        577,
        1142
      ],
      "right_shoulder": [
        284,
        579,
        1159
      ],
      "left_elbow": [
        -154,
        469,
        1425
      ],
      "right_elbow": [
        344,
        508,
        1400
      ],
      "left_wrist": [
        -151,
        293,
        1541
      ],
      "right_wrist": [
        262,
        345,
        1562
      ]
    }
  },
  {
    "frame_id": 85,
    "keypoint_xyz": {
      "left_ear": [
        15,
        473,
        951
      ],
      "right_ear": [
        130,
        439,
        898
      ],
      "left_shoulder": [
        -109,
        578,
        1141
      ],
      "right_shoulder": [
        282,
        582,
        1157
      ],
      "left_elbow": [
        -153,
        465,
        1427
      ],
      "right_elbow": [
        348,
        515,
        1398
      ],
      "left_wrist": [
        -152,
        291,
        1545
      ],
      "right_wrist": [
        261,
        348,
        1564
      ]
    }
  },
  {
    "frame_id": 86,
    "keypoint_xyz": {
      "left_ear": [
        16,
        473,
        953
      ],
      "right_ear": [
        132,
        439,
        903
      ],
      "left_shoulder": [
        -109,
        579,
        1141
      ],
      "right_shoulder": [
        286,
        580,
        1158
      ],
      "left_elbow": [
        -159,
        468,
        1426
      ],
      "right_elbow": [
        344,
        509,
        1399
      ],
      "left_wrist": [
        -152,
        291,
        1546
      ],
      "right_wrist": [
        263,
        345,
        1567
      ]
    }
  },
  {
    "frame_id": 87,
    "keypoint_xyz": {
      "left_ear": [
        15,
        478,
        966
      ],
      "right_ear": [
        130,
        437,
        903
      ],
      "left_shoulder": [
        -109,
        579,
        1141
      ],
      "right_shoulder": [
        283,
        583,
        1154
      ],
      "left_elbow": [
        -153,
        466,
        1425
      ],
      "right_elbow": [
        345,
        512,
        1400
      ],
      "left_wrist": [
        -152,
        289,
        1546
      ],
      "right_wrist": [
        261,
        346,
        1566
      ]
    }
  }
]